{
  "version": "1.0",
  "photos": [
    {
      "photo_id": "2025-11-04-Maastricht-maas-walk-dsc-0223",
      "series_slug": "routes",
      "sub_pool_slug": null,
      "hero_url": "https://photos.studiotj.com/2025-11-04-Maastricht-maas-walk/DSC_0223-hero.webp",
      "thumb_url": "https://photos.studiotj.com/2025-11-04-Maastricht-maas-walk/DSC_0223-thumb.webp",
      "width": 1600,
      "height": 1066,
      "alt": "Road bridge over the Maas river, backlit autumn afternoon, Maastricht.",
      "shoot_date": "2025-11-04",
      "datetime_original": null,
      "route_slug": "maastricht-along-the-maas",
      "route_display_name": null
    },
    {
      "photo_id": "2025-11-04-Maastricht-maas-walk-dsc-0225",
      "series_slug": "routes",
      "sub_pool_slug": null,
      "hero_url": "https://photos.studiotj.com/2025-11-04-Maastricht-maas-walk/DSC_0225-hero.webp",
      "thumb_url": "https://photos.studiotj.com/2025-11-04-Maastricht-maas-walk/DSC_0225-thumb.webp",
      "width": 1066,
      "height": 1600,
      "alt": "Domed observatory tower seen from low angle, Maastricht.",
      "shoot_date": "2025-11-04",
      "datetime_original": null,
      "route_slug": "maastricht-along-the-maas",
      "route_display_name": null
    },
    {
      "photo_id": "2025-11-04-Maastricht-maas-walk-dsc-0232",
      "series_slug": "routes",
      "sub_pool_slug": null,
      "hero_url": "https://photos.studiotj.com/2025-11-04-Maastricht-maas-walk/DSC_0232-hero.webp",
      "thumb_url": "https://photos.studiotj.com/2025-11-04-Maastricht-maas-walk/DSC_0232-thumb.webp",
      "width": 1066,
      "height": 1600,
      "alt": "Low-angle view beneath concrete road bridge over the Maas, Maastricht, autumn.",
      "shoot_date": "2025-11-04",
      "datetime_original": null,
      "route_slug": "maastricht-along-the-maas",
      "route_display_name": null
    },
    {
      "photo_id": "2025-11-04-Maastricht-maas-walk-dsc-0233",
      "series_slug": "routes",
      "sub_pool_slug": null,
      "hero_url": "https://photos.studiotj.com/2025-11-04-Maastricht-maas-walk/DSC_0233-hero.webp",
      "thumb_url": "https://photos.studiotj.com/2025-11-04-Maastricht-maas-walk/DSC_0233-thumb.webp",
      "width": 1600,
      "height": 1066,
      "alt": "Underside of concrete road bridge over the Maas, Maastricht.",
      "shoot_date": "2025-11-04",
      "datetime_original": null,
      "route_slug": "maastricht-along-the-maas",
      "route_display_name": null
    },
    {
      "photo_id": "2025-11-04-Maastricht-maas-walk-dsc-0240",
      "series_slug": "routes",
      "sub_pool_slug": null,
      "hero_url": "https://photos.studiotj.com/2025-11-04-Maastricht-maas-walk/DSC_0240-hero.webp",
      "thumb_url": "https://photos.studiotj.com/2025-11-04-Maastricht-maas-walk/DSC_0240-thumb.webp",
      "width": 1600,
      "height": 1066,
      "alt": "Underside of concrete road bridge over the Maas, Maastricht.",
      "shoot_date": "2025-11-04",
      "datetime_original": null,
      "route_slug": "maastricht-along-the-maas",
      "route_display_name": null
    },
    {
      "photo_id": "2025-11-04-Maastricht-maas-walk-dsc-0243",
      "series_slug": "routes",
      "sub_pool_slug": null,
      "hero_url": "https://photos.studiotj.com/2025-11-04-Maastricht-maas-walk/DSC_0243-hero.webp",
      "thumb_url": "https://photos.studiotj.com/2025-11-04-Maastricht-maas-walk/DSC_0243-thumb.webp",
      "width": 1066,
      "height": 1600,
      "alt": "Construction traffic warning sign beneath concrete road bridge over the Maas, Maastricht.",
      "shoot_date": "2025-11-04",
      "datetime_original": null,
      "route_slug": "maastricht-along-the-maas",
      "route_display_name": null
    },
    {
      "photo_id": "2025-11-04-Maastricht-maas-walk-dsc-0245",
      "series_slug": "routes",
      "sub_pool_slug": null,
      "hero_url": "https://photos.studiotj.com/2025-11-04-Maastricht-maas-walk/DSC_0245-hero.webp",
      "thumb_url": "https://photos.studiotj.com/2025-11-04-Maastricht-maas-walk/DSC_0245-thumb.webp",
      "width": 1600,
      "height": 1066,
      "alt": "Modern concrete road bridge spanning the Maas river, viewed from the riverbank, Maastricht.",
      "shoot_date": "2025-11-04",
      "datetime_original": null,
      "route_slug": "maastricht-along-the-maas",
      "route_display_name": null
    },
    {
      "photo_id": "2025-11-04-Maastricht-maas-walk-dsc-0252",
      "series_slug": "routes",
      "sub_pool_slug": null,
      "hero_url": "https://photos.studiotj.com/2025-11-04-Maastricht-maas-walk/DSC_0252-hero.webp",
      "thumb_url": "https://photos.studiotj.com/2025-11-04-Maastricht-maas-walk/DSC_0252-thumb.webp",
      "width": 1600,
      "height": 1066,
      "alt": "Elevated brick and concrete bridge building on pilotis, Maastricht.",
      "shoot_date": "2025-11-04",
      "datetime_original": null,
      "route_slug": "maastricht-along-the-maas",
      "route_display_name": null
    },
    {
      "photo_id": "2025-11-04-Maastricht-maas-walk-dsc-0262",
      "series_slug": "routes",
      "sub_pool_slug": null,
      "hero_url": "https://photos.studiotj.com/2025-11-04-Maastricht-maas-walk/DSC_0262-hero.webp",
      "thumb_url": "https://photos.studiotj.com/2025-11-04-Maastricht-maas-walk/DSC_0262-thumb.webp",
      "width": 1600,
      "height": 1066,
      "alt": "Concrete pilotis underpass beside canal, brick building above, Maastricht.",
      "shoot_date": "2025-11-04",
      "datetime_original": null,
      "route_slug": "maastricht-along-the-maas",
      "route_display_name": null
    },
    {
      "photo_id": "2025-11-04-Maastricht-maas-walk-dsc-0264",
      "series_slug": "routes",
      "sub_pool_slug": null,
      "hero_url": "https://photos.studiotj.com/2025-11-04-Maastricht-maas-walk/DSC_0264-hero.webp",
      "thumb_url": "https://photos.studiotj.com/2025-11-04-Maastricht-maas-walk/DSC_0264-thumb.webp",
      "width": 1066,
      "height": 1600,
      "alt": "Underside of concrete pavilion structure over still water, Maastricht.",
      "shoot_date": "2025-11-04",
      "datetime_original": null,
      "route_slug": "maastricht-along-the-maas",
      "route_display_name": null
    },
    {
      "photo_id": "2025-11-04-Maastricht-maas-walk-dsc-0266",
      "series_slug": "routes",
      "sub_pool_slug": null,
      "hero_url": "https://photos.studiotj.com/2025-11-04-Maastricht-maas-walk/DSC_0266-hero.webp",
      "thumb_url": "https://photos.studiotj.com/2025-11-04-Maastricht-maas-walk/DSC_0266-thumb.webp",
      "width": 1600,
      "height": 1066,
      "alt": "Modern brick faculty building elevated on concrete pilotis over water, Maastricht.",
      "shoot_date": "2025-11-04",
      "datetime_original": null,
      "route_slug": "maastricht-along-the-maas",
      "route_display_name": null
    },
    {
      "photo_id": "2025-11-04-Maastricht-maas-walk-dsc-0268",
      "series_slug": "routes",
      "sub_pool_slug": null,
      "hero_url": "https://photos.studiotj.com/2025-11-04-Maastricht-maas-walk/DSC_0268-hero.webp",
      "thumb_url": "https://photos.studiotj.com/2025-11-04-Maastricht-maas-walk/DSC_0268-thumb.webp",
      "width": 1600,
      "height": 1066,
      "alt": "Modernist civic building with Dutch and provincial flags, viewed from the water, Maastricht.",
      "shoot_date": "2025-11-04",
      "datetime_original": null,
      "route_slug": "maastricht-along-the-maas",
      "route_display_name": null
    },
    {
      "photo_id": "2025-11-04-Maastricht-maas-walk-dsc-0272",
      "series_slug": "routes",
      "sub_pool_slug": null,
      "hero_url": "https://photos.studiotj.com/2025-11-04-Maastricht-maas-walk/DSC_0272-hero.webp",
      "thumb_url": "https://photos.studiotj.com/2025-11-04-Maastricht-maas-walk/DSC_0272-thumb.webp",
      "width": 1066,
      "height": 1600,
      "alt": "Underside of concrete road bridge over the Maas, with flagpoles and willow, Maastricht.",
      "shoot_date": "2025-11-04",
      "datetime_original": null,
      "route_slug": "maastricht-along-the-maas",
      "route_display_name": null
    },
    {
      "photo_id": "2025-11-04-Maastricht-maas-walk-dsc-0274",
      "series_slug": "routes",
      "sub_pool_slug": null,
      "hero_url": "https://photos.studiotj.com/2025-11-04-Maastricht-maas-walk/DSC_0274-hero.webp",
      "thumb_url": "https://photos.studiotj.com/2025-11-04-Maastricht-maas-walk/DSC_0274-thumb.webp",
      "width": 1600,
      "height": 1066,
      "alt": "Brutalist theatre complex viewed across the Maas river, Maastricht.",
      "shoot_date": "2025-11-04",
      "datetime_original": null,
      "route_slug": "maastricht-along-the-maas",
      "route_display_name": null
    },
    {
      "photo_id": "2025-11-04-Maastricht-maas-walk-dsc-0278",
      "series_slug": "routes",
      "sub_pool_slug": null,
      "hero_url": "https://photos.studiotj.com/2025-11-04-Maastricht-maas-walk/DSC_0278-hero.webp",
      "thumb_url": "https://photos.studiotj.com/2025-11-04-Maastricht-maas-walk/DSC_0278-thumb.webp",
      "width": 1066,
      "height": 1600,
      "alt": "Wooden gate beneath autumn oak canopy, riverside path, Maastricht.",
      "shoot_date": "2025-11-04",
      "datetime_original": null,
      "route_slug": "maastricht-along-the-maas",
      "route_display_name": null
    },
    {
      "photo_id": "2025-11-04-Maastricht-maas-walk-dsc-0280",
      "series_slug": "routes",
      "sub_pool_slug": null,
      "hero_url": "https://photos.studiotj.com/2025-11-04-Maastricht-maas-walk/DSC_0280-hero.webp",
      "thumb_url": "https://photos.studiotj.com/2025-11-04-Maastricht-maas-walk/DSC_0280-thumb.webp",
      "width": 1066,
      "height": 1599,
      "alt": "Paved rural path stretching toward backlit sun, Maastricht outskirts.",
      "shoot_date": "2025-11-04",
      "datetime_original": null,
      "route_slug": "maastricht-along-the-maas",
      "route_display_name": null
    },
    {
      "photo_id": "2025-11-04-Maastricht-maas-walk-dsc-0288",
      "series_slug": "routes",
      "sub_pool_slug": null,
      "hero_url": "https://photos.studiotj.com/2025-11-04-Maastricht-maas-walk/DSC_0288-hero.webp",
      "thumb_url": "https://photos.studiotj.com/2025-11-04-Maastricht-maas-walk/DSC_0288-thumb.webp",
      "width": 1066,
      "height": 1600,
      "alt": "Wooden pedestrian bridge leading into autumn woodland, Maastricht.",
      "shoot_date": "2025-11-04",
      "datetime_original": null,
      "route_slug": "maastricht-along-the-maas",
      "route_display_name": null
    },
    {
      "photo_id": "2025-11-04-Maastricht-maas-walk-dsc-0298",
      "series_slug": "routes",
      "sub_pool_slug": null,
      "hero_url": "https://photos.studiotj.com/2025-11-04-Maastricht-maas-walk/DSC_0298-hero.webp",
      "thumb_url": "https://photos.studiotj.com/2025-11-04-Maastricht-maas-walk/DSC_0298-thumb.webp",
      "width": 1066,
      "height": 1600,
      "alt": "Church spire silhouetted through riverside trees across the Maas, Maastricht.",
      "shoot_date": "2025-11-04",
      "datetime_original": null,
      "route_slug": "maastricht-along-the-maas",
      "route_display_name": null
    },
    {
      "photo_id": "2025-11-04-Maastricht-maas-walk-dsc-0302",
      "series_slug": "routes",
      "sub_pool_slug": null,
      "hero_url": "https://photos.studiotj.com/2025-11-04-Maastricht-maas-walk/DSC_0302-hero.webp",
      "thumb_url": "https://photos.studiotj.com/2025-11-04-Maastricht-maas-walk/DSC_0302-thumb.webp",
      "width": 1066,
      "height": 1600,
      "alt": "Wooden pedestrian bridge crossing a river channel, Maastricht.",
      "shoot_date": "2025-11-04",
      "datetime_original": null,
      "route_slug": "maastricht-along-the-maas",
      "route_display_name": null
    }
  ]
}
